README.md
setup.py
parhugin/__init__.py
parhugin/multi_func.py
parhugin/utils.py
parhugin.egg-info/PKG-INFO
parhugin.egg-info/SOURCES.txt
parhugin.egg-info/dependency_links.txt
parhugin.egg-info/entry_points.txt
parhugin.egg-info/not-zip-safe
parhugin.egg-info/top_level.txt